{"nodes": [{"id": "c_users_administrator_desktop_project2_flutter_application_1_lib_widgets_zakat_widget_dart", "label": "zakat_widget.dart", "file_type": "code", "source_file": "lib/widgets/zakat_widget.dart", "source_location": null}, {"id": "widgets_zakat_widget_zakatwidgetservice", "label": "ZakatWidgetService", "file_type": "code", "source_file": "lib/widgets/zakat_widget.dart", "source_location": null}, {"id": "widgets_zakat_widget_appgroupid", "label": "_appGroupId", "file_type": "code", "source_file": "lib/widgets/zakat_widget.dart", "source_location": null}, {"id": "static_const_string", "label": "static const String", "file_type": "code", "source_file": null, "source_location": null}, {"id": "widgets_zakat_widget_ioswidgetname", "label": "_iOSWidgetName", "file_type": "code", "source_file": "lib/widgets/zakat_widget.dart", "source_location": null}, {"id": "widgets_zakat_widget_androidwidgetname", "label": "_androidWidgetName", "file_type": "code", "source_file": "lib/widgets/zakat_widget.dart", "source_location": null}, {"id": "widgets_zakat_widget_init", "label": "init", "file_type": "code", "source_file": "lib/widgets/zakat_widget.dart", "source_location": null}, {"id": "widgets_zakat_widget_updatewidget", "label": "updateWidget", "file_type": "code", "source_file": "lib/widgets/zakat_widget.dart", "source_location": null}, {"id": "widgets_zakat_widget_listenforwidgettap", "label": "listenForWidgetTap", "file_type": "code", "source_file": "lib/widgets/zakat_widget.dart", "source_location": null}, {"id": "widgets_zakat_widget_getinitialwidgeturi", "label": "getInitialWidgetUri", "file_type": "code", "source_file": "lib/widgets/zakat_widget.dart", "source_location": null}, {"id": "package_home_widget_home_widget_dart", "label": "package:home_widget/home_widget.dart", "file_type": "code", "source_file": null, "source_location": null}, {"id": "models_zakat_provider_dart", "label": "../models/zakat_provider.dart", "file_type": "code", "source_file": null, "source_location": null}], "edges": [{"source": "c_users_administrator_desktop_project2_flutter_application_1_lib_widgets_zakat_widget_dart", "target": "widgets_zakat_widget_zakatwidgetservice", "relation": "defines", "confidence": "EXTRACTED", "confidence_score": 1.0, "source_file": "lib/widgets/zakat_widget.dart", "source_location": null, "weight": 1.0}, {"source": "c_users_administrator_desktop_project2_flutter_application_1_lib_widgets_zakat_widget_dart", "target": "widgets_zakat_widget_appgroupid", "relation": "defines", "confidence": "EXTRACTED", "confidence_score": 1.0, "source_file": "lib/widgets/zakat_widget.dart", "source_location": null, "weight": 1.0}, {"source": "c_users_administrator_desktop_project2_flutter_application_1_lib_widgets_zakat_widget_dart", "target": "static_const_string", "relation": "references", "confidence": "EXTRACTED", "confidence_score": 1.0, "source_file": "lib/widgets/zakat_widget.dart", "source_location": null, "weight": 1.0, "context": "variable_type"}, {"source": "c_users_administrator_desktop_project2_flutter_application_1_lib_widgets_zakat_widget_dart", "target": "widgets_zakat_widget_ioswidgetname", "relation": "defines", "confidence": "EXTRACTED", "confidence_score": 1.0, "source_file": "lib/widgets/zakat_widget.dart", "source_location": null, "weight": 1.0}, {"source": "c_users_administrator_desktop_project2_flutter_application_1_lib_widgets_zakat_widget_dart", "target": "static_const_string", "relation": "references", "confidence": "EXTRACTED", "confidence_score": 1.0, "source_file": "lib/widgets/zakat_widget.dart", "source_location": null, "weight": 1.0, "context": "variable_type"}, {"source": "c_users_administrator_desktop_project2_flutter_application_1_lib_widgets_zakat_widget_dart", "target": "widgets_zakat_widget_androidwidgetname", "relation": "defines", "confidence": "EXTRACTED", "confidence_score": 1.0, "source_file": "lib/widgets/zakat_widget.dart", "source_location": null, "weight": 1.0}, {"source": "c_users_administrator_desktop_project2_flutter_application_1_lib_widgets_zakat_widget_dart", "target": "static_const_string", "relation": "references", "confidence": "EXTRACTED", "confidence_score": 1.0, "source_file": "lib/widgets/zakat_widget.dart", "source_location": null, "weight": 1.0, "context": "variable_type"}, {"source": "c_users_administrator_desktop_project2_flutter_application_1_lib_widgets_zakat_widget_dart", "target": "widgets_zakat_widget_init", "relation": "defines", "confidence": "EXTRACTED", "confidence_score": 1.0, "source_file": "lib/widgets/zakat_widget.dart", "source_location": null, "weight": 1.0}, {"source": "c_users_administrator_desktop_project2_flutter_application_1_lib_widgets_zakat_widget_dart", "target": "widgets_zakat_widget_updatewidget", "relation": "defines", "confidence": "EXTRACTED", "confidence_score": 1.0, "source_file": "lib/widgets/zakat_widget.dart", "source_location": null, "weight": 1.0}, {"source": "c_users_administrator_desktop_project2_flutter_application_1_lib_widgets_zakat_widget_dart", "target": "widgets_zakat_widget_listenforwidgettap", "relation": "defines", "confidence": "EXTRACTED", "confidence_score": 1.0, "source_file": "lib/widgets/zakat_widget.dart", "source_location": null, "weight": 1.0}, {"source": "c_users_administrator_desktop_project2_flutter_application_1_lib_widgets_zakat_widget_dart", "target": "widgets_zakat_widget_getinitialwidgeturi", "relation": "defines", "confidence": "EXTRACTED", "confidence_score": 1.0, "source_file": "lib/widgets/zakat_widget.dart", "source_location": null, "weight": 1.0}, {"source": "c_users_administrator_desktop_project2_flutter_application_1_lib_widgets_zakat_widget_dart", "target": "package_home_widget_home_widget_dart", "relation": "imports", "confidence": "EXTRACTED", "confidence_score": 1.0, "source_file": "lib/widgets/zakat_widget.dart", "source_location": null, "weight": 1.0}, {"source": "c_users_administrator_desktop_project2_flutter_application_1_lib_widgets_zakat_widget_dart", "target": "models_zakat_provider_dart", "relation": "imports", "confidence": "EXTRACTED", "confidence_score": 1.0, "source_file": "lib/widgets/zakat_widget.dart", "source_location": null, "weight": 1.0}]}